LICENSE
README.md
setup.cfg
setup.py
amari/__init__.py
amari/openai/__init__.py
amari/openai/_openai_scripts.py
amari/openai/api_requestor.py
amari/openai/cli.py
amari/openai/embeddings_utils.py
amari/openai/error.py
amari/openai/object_classes.py
amari/openai/openai_object.py
amari/openai/openai_response.py
amari/openai/upload_progress.py
amari/openai/util.py
amari/openai/validators.py
amari/openai/version.py
amari/openai/wandb_logger.py
amari/openai/api_resources/__init__.py
amari/openai/api_resources/audio.py
amari/openai/api_resources/chat_completion.py
amari/openai/api_resources/completion.py
amari/openai/api_resources/customer.py
amari/openai/api_resources/deployment.py
amari/openai/api_resources/edit.py
amari/openai/api_resources/embedding.py
amari/openai/api_resources/engine.py
amari/openai/api_resources/error_object.py
amari/openai/api_resources/file.py
amari/openai/api_resources/fine_tune.py
amari/openai/api_resources/fine_tuning.py
amari/openai/api_resources/image.py
amari/openai/api_resources/model.py
amari/openai/api_resources/moderation.py
amari/openai/api_resources/abstract/__init__.py
amari/openai/api_resources/abstract/api_resource.py
amari/openai/api_resources/abstract/createable_api_resource.py
amari/openai/api_resources/abstract/deletable_api_resource.py
amari/openai/api_resources/abstract/engine_api_resource.py
amari/openai/api_resources/abstract/listable_api_resource.py
amari/openai/api_resources/abstract/nested_resource_class_methods.py
amari/openai/api_resources/abstract/paginatable_api_resource.py
amari/openai/api_resources/abstract/updateable_api_resource.py
amari/openai/api_resources/experimental/__init__.py
amari/openai/api_resources/experimental/completion_config.py
amari/openai/datalib/__init__.py
amari/openai/datalib/common.py
amari/openai/datalib/numpy_helper.py
amari/openai/datalib/pandas_helper.py
amari_python.egg-info/PKG-INFO
amari_python.egg-info/SOURCES.txt
amari_python.egg-info/dependency_links.txt
amari_python.egg-info/entry_points.txt
amari_python.egg-info/requires.txt
amari_python.egg-info/top_level.txt
amari_python.egg-info/zip-safe